README.txt
setup.py
corenlp/__init__.py
corenlp/pipeline.py
corenlp.egg-info/PKG-INFO
corenlp.egg-info/SOURCES.txt
corenlp.egg-info/dependency_links.txt
corenlp.egg-info/requires.txt
corenlp.egg-info/top_level.txt