Metadata-Version: 1.0
Name: corenlp
Version: 0.0.4
Summary: A python wrapper for the Stanford CoreNLP java library.
Home-page: www.github.com/kedz
Author: Chris Kedzie
Author-email: kedzie@cs.columbia.edu
License: UNKNOWN
Platform: UNKNOWN
